{"acteur": {"@xmlns:xsi": "http://www.w3.org/2001/XMLSchema-instance", "uid": {"@xsi:type": "IdActeur_type", "#text": "PA721170"}, "etatCivil": {"ident": {"civ": "M.", "prenom": "St\u00e9phane", "nom": "Vojetta", "alpha": "Vojetta", "trigramme": "SVOJ"}, "infoNaissance": {"dateNais": "1974-07-19", "villeNais": "Nancy", "depNais": "Meurthe-et-Moselle", "paysNais": "France"}, "dateDeces": null}, "profession": {"libelleCourant": "Entrepreneur", "socProcINSEE": {"catSocPro": "Chefs d'entreprise de 10 salari\u00e9s ou plus", "famSocPro": "Artisans, commer\u00e7ants et chefs d'entreprise"}}, "uri_hatvp": null, "adresses": {"adresse": [{"@xsi:type": "AdressePostale_Type", "uid": "AD721172", "type": "0", "typeLibelle": "Adresse officielle", "poids": "1", "adresseDeRattachement": null, "intitule": "Assembl\u00e9e nationale,", "numeroRue": "126", "nomRue": "Rue de l'Universit\u00e9,", "complementAdresse": null, "codePostal": "75355", "ville": "Paris 07 SP"}, {"@xsi:type": "AdresseMail_Type", "uid": "AD786563", "type": "15", "typeLibelle": "M\u00e8l", "poids": null, "adresseDeRattachement": null, "valElec": "stephane.vojetta@assemblee-nationale.fr"}, {"@xsi:type": "AdresseSiteWeb_Type", "uid": "AD787777", "type": "22", "typeLibelle": "Site internet", "poids": null, "adresseDeRattachement": null, "valElec": "stephane-vojetta.com"}, {"@xsi:type": "AdresseSiteWeb_Type", "uid": "AD798221", "type": "25", "typeLibelle": "Facebook", "poids": null, "adresseDeRattachement": null, "valElec": "stephanevojettaofficiel"}, {"@xsi:type": "AdresseSiteWeb_Type", "uid": "AD798225", "type": "24", "typeLibelle": "Twitter", "poids": null, "adresseDeRattachement": null, "valElec": "@StephaneVojetta"}]}}}