{"acteur": {"@xmlns:xsi": "http://www.w3.org/2001/XMLSchema-instance", "uid": {"@xsi:type": "IdActeur_type", "#text": "PA793508"}, "etatCivil": {"ident": {"civ": "M.", "prenom": "Hubert", "nom": "Brigand", "alpha": "Brigand", "trigramme": "HBI"}, "infoNaissance": {"dateNais": "1952-07-28", "villeNais": "Chatillon-sur-Seine", "depNais": "C\u00f4te-d'Or", "paysNais": "France"}, "dateDeces": null}, "profession": {"libelleCourant": "Ancienne profession interm\u00e9diaire", "socProcINSEE": {"catSocPro": "Anciens cadres et professions interm\u00e9diaires", "famSocPro": "Retrait\u00e9s"}}, "uri_hatvp": null, "adresses": {"adresse": [{"@xsi:type": "AdressePostale_Type", "uid": "AD793510", "type": "0", "typeLibelle": "Adresse officielle", "poids": "1", "adresseDeRattachement": null, "intitule": "Assembl\u00e9e nationale,", "numeroRue": "126", "nomRue": "Rue de l'Universit\u00e9,", "complementAdresse": null, "codePostal": "75355", "ville": "Paris 07 SP"}, {"@xsi:type": "AdresseMail_Type", "uid": "AD797928", "type": "15", "typeLibelle": "M\u00e8l", "poids": null, "adresseDeRattachement": null, "valElec": "hubert.brigand@assemblee-nationale.fr"}, {"@xsi:type": "AdressePostale_Type", "uid": "AD799347", "type": "2", "typeLibelle": "Adresse publi\u00e9e de circonscription", "poids": "22", "adresseDeRattachement": null, "intitule": null, "numeroRue": "1", "nomRue": "Place de la r\u00e9sistance", "complementAdresse": null, "codePostal": "21400", "ville": "Chatillon-sur-Seine"}]}}}