{"acteur": {"@xmlns:xsi": "http://www.w3.org/2001/XMLSchema-instance", "uid": {"@xsi:type": "IdActeur_type", "#text": "PA841645"}, "etatCivil": {"ident": {"civ": "M.", "prenom": "Th\u00e9o", "nom": "Bernhardt", "alpha": "Bernhardt", "trigramme": "TBR"}, "infoNaissance": {"dateNais": "2000-06-29", "villeNais": "Angers", "depNais": "Maine-et-Loire", "paysNais": "France"}, "dateDeces": null}, "profession": {"libelleCourant": "(84) - El\u00e8ve, \u00e9tudiant", "socProcINSEE": {"catSocPro": "Sans profession d\u00e9clar\u00e9e", "famSocPro": "Sans profession d\u00e9clar\u00e9e"}}, "uri_hatvp": null, "adresses": {"adresse": [{"@xsi:type": "AdressePostale_Type", "uid": "AD841647", "type": "0", "typeLibelle": "Adresse officielle", "poids": "1", "adresseDeRattachement": null, "intitule": "Assembl\u00e9e nationale,", "numeroRue": "126", "nomRue": "Rue de l'Universit\u00e9,", "complementAdresse": null, "codePostal": "75355", "ville": "Paris 07 SP"}, {"@xsi:type": "AdresseMail_Type", "uid": "AD843913", "type": "15", "typeLibelle": "M\u00e8l", "poids": null, "adresseDeRattachement": null, "valElec": "theo.bernhardt@assemblee-nationale.fr"}, {"@xsi:type": "AdresseSiteWeb_Type", "uid": "AD844988", "type": "24", "typeLibelle": "Twitter", "poids": null, "adresseDeRattachement": null, "valElec": "@Th_Bnrdt"}]}}}